BUGS
FAQ
HACKING
INSTALL.FreeBSD
PKG-INFO
README
README.JAWS
TODO
freedots.desktop
setup.cfg
setup.py
doc/DejaVuSerif.ttf
doc/DejaVuSerif.xml
doc/fop.xml
doc/html.xsl
doc/manual.xml
doc/pdf-a4.xsl
doc/pdf.xsl
doc/unicode-braille-v10.ent
freedots/COPYING
freedots/__init__.py
freedots/braillemusic.py
freedots/frontend.py
freedots/gui.py
freedots/music.py
freedots/musicxml.py
freedots/playback.py
freedots/viewer.py
freedots.egg-info/PKG-INFO
freedots.egg-info/SOURCES.txt
freedots.egg-info/dependency_links.txt
freedots.egg-info/entry_points.txt
freedots.egg-info/requires.txt
freedots.egg-info/top_level.txt
freedots/utils/ElementPath.py
freedots/utils/ElementTree.py
freedots/utils/__init__.py
freedots/utils/midi.py
freedots/utils/rational.py
input/README
input/audiveris/BeetAnGeSample-250.xml
input/audiveris/bwv999.xml
input/audiveris/chula.xml
input/capella-scan/bwv988-aria.xml
input/photoscore/air_for_flute.xml
input/photoscore/bwv1010-prelude.xml
input/photoscore/bwv1013.xml
input/photoscore/bwv999.xml
input/photoscore/moonlight1.xml
input/sharpeye/bwv1013.xml
input/sources/bwv1010-prelude.pdf
input/sources/bwv999.pdf
input/sources/moonlight1-a4.ly
tests/musicxml/articulations.xml
tests/musicxml/chord.xml
tests/musicxml/clef.xml
tests/musicxml/key.xml
tests/musicxml/tie_slur.xml