Metadata-Version: 1.0
Name: freedots
Version: 0.3
Summary: MusicXML to Braille music translation
Home-page: UNKNOWN
Author: Mario Lang
Author-email: mlang@delysid.org
License: GPL
Keywords: braille,music notation,musicxml,midi,gtk
Platform: UNKNOWN
